githubsocial/GithubUser.py
githubsocial/__init__.py
githubsocial/main.py
github_social-0.1.1.dist-info/LICENSE
github_social-0.1.1.dist-info/METADATA
github_social-0.1.1.dist-info/WHEEL
github_social-0.1.1.dist-info/top_level.txt
github_social-0.1.1.dist-info/RECORD
