Metadata-Version: 2.1
Name: github-social
Version: 0.1.1
Summary: A helper for github users managing their accounts as social accounts.
Home-page: https://github.com/PapaSinku/github-social
Author: Sinku
Author-email: sininoir@gmail.com
Classifier: Programming Language :: Python :: 3
Classifier: License :: OSI Approved :: MIT License
Classifier: Operating System :: OS Independent
Requires-Python: >=3.7
License-File: LICENSE
Requires-Dist: beautifulsoup4 (==4.11.1)
Requires-Dist: mypy-extensions (==0.4.3)
Requires-Dist: pathspec (==0.9.0)
Requires-Dist: platformdirs (==2.5.2)
Requires-Dist: soupsieve (==2.3.2.post1)
Requires-Dist: tomli (==2.0.1)
Requires-Dist: typing-extensions (==4.3.0)
